LICENSE
README.md
setup.py
servo_voltage/JsonWorker.py
servo_voltage/ServoVoltage.py
servo_voltage/__init__.py
servo_voltage.egg-info/PKG-INFO
servo_voltage.egg-info/SOURCES.txt
servo_voltage.egg-info/dependency_links.txt
servo_voltage.egg-info/requires.txt
servo_voltage.egg-info/top_level.txt