Metadata-Version: 2.1
Name: servo-voltage
Version: 0.0.1
Summary: Read voltage data for feetech servo
Home-page: https://github.com/Adam-Software/Servo-voltage
Author: vertigra
Author-email: a@nesterof.com
License: MIT
Platform: UNKNOWN
Classifier: Development Status :: 3 - Alpha
Classifier: License :: OSI Approved :: MIT License
Classifier: Operating System :: POSIX :: Other
Classifier: Programming Language :: Python :: 3.7
Classifier: Programming Language :: Python :: 3.8
Classifier: Programming Language :: Python :: 3.9
License-File: LICENSE
